pgo/__init__.py
pgo/setuptools/__init__.py
pgo/setuptools/build.py
pgo/setuptools/clean.py
pgo/setuptools/command.py
pgo/setuptools/compiler.py
pgo/setuptools/extend.py
pgo/setuptools/install_lib.py
pgo/setuptools/profile.py
pgo/setuptools/profilegen.py
pgo/setuptools/profileuse.py
pgo/setuptools/util.py
pgo-0.2.2.dist-info/LICENSE
pgo-0.2.2.dist-info/METADATA
pgo-0.2.2.dist-info/WHEEL
pgo-0.2.2.dist-info/entry_points.txt
pgo-0.2.2.dist-info/top_level.txt
pgo-0.2.2.dist-info/RECORD
